djshorty-0.5.5.dist-info/DESCRIPTION.rst
djshorty-0.5.5.dist-info/METADATA
djshorty-0.5.5.dist-info/RECORD
djshorty-0.5.5.dist-info/WHEEL
djshorty-0.5.5.dist-info/metadata.json
djshorty-0.5.5.dist-info/top_level.txt
shorty/__init__.py
shorty/admin.py
shorty/app_settings.py
shorty/autoconfig.py
shorty/forms.py
shorty/models.py
shorty/tests.py
shorty/urls.py
shorty/version.py
shorty/views.py
shorty/migrations/0001_initial.py
shorty/migrations/0002_auto_20160322_1720.py
shorty/migrations/0003_auto_20160602_1131.py
shorty/migrations/0004_auto_20160802_2054.py
shorty/migrations/__init__.py
shorty/static/shorty.css
shorty/static/shorty.js
shorty/templates/shorty/home.html
shorty/templates/shorty/preview.html
shorty/templates/shorty/shorturl_list.html
shorty/templatetags/__init__.py
shorty/templatetags/shorty.py
