Metadata-Version: 2.0
Name: djshorty
Version: 0.5.5
Summary: A Django URL shortening app
Home-page: UNKNOWN
Author: Ben Cardy
Author-email: ben.cardy@ocado.com
License: UNKNOWN
Platform: UNKNOWN
Classifier: License :: OSI Approved :: Apache Software License
Requires-Dist: django (<1.10.0)
Requires-Dist: django-autoconfig (>=0.5.0)
Requires-Dist: django-nuit (>=1.0.0,<2.0.0)
